presume/__init__.py
presume/presume.py
presume/then.py
presume-0.1.dist-info/DESCRIPTION.rst
presume-0.1.dist-info/METADATA
presume-0.1.dist-info/RECORD
presume-0.1.dist-info/WHEEL
presume-0.1.dist-info/metadata.json
presume-0.1.dist-info/top_level.txt
