Metadata-Version: 2.0
Name: presume
Version: 0.1
Summary: decorator handling exception
Home-page: https://github.com/willhyper/pyplin.git
Author: Chao-Wei Chen
Author-email: willhyper@gmail.com
License: MIT
Download-URL: https://github.com/willhyper/presume/archive/master.zip
Keywords: decorator,exception
Platform: UNKNOWN
Requires-Python: >=3.3
